swagger2locustio/__init__.py
swagger2locustio/__main__.py
swagger2locustio/utils.py
swagger2locustio/__pycache__/__init__.cpython-38.pyc
swagger2locustio/__pycache__/__main__.cpython-38-pytest-5.4.1.pyc
swagger2locustio/__pycache__/__main__.cpython-38.pyc
swagger2locustio/__pycache__/settings.cpython-38-pytest-5.4.1.pyc
swagger2locustio/__pycache__/utils.cpython-38.pyc
swagger2locustio/generators/__init__.py
swagger2locustio/generators/base_generator.py
swagger2locustio/generators/__pycache__/__init__.cpython-38.pyc
swagger2locustio/generators/__pycache__/base_generator.cpython-38-pytest-5.4.1.pyc
swagger2locustio/generators/__pycache__/base_generator.cpython-38.pyc
swagger2locustio/parsers/__init__.py
swagger2locustio/parsers/base_parser.py
swagger2locustio/parsers/swagger_v2.py
swagger2locustio/parsers/swagger_v3.py
swagger2locustio/parsers/__pycache__/__init__.cpython-38.pyc
swagger2locustio/parsers/__pycache__/base_parser.cpython-38-pytest-5.4.1.pyc
swagger2locustio/parsers/__pycache__/base_parser.cpython-38.pyc
swagger2locustio/parsers/__pycache__/swagger_v2.cpython-38.pyc
swagger2locustio/parsers/__pycache__/swagger_v3.cpython-38.pyc
swagger2locustio/parsers/json_parsers/__pycache__/__init__.cpython-38.pyc
swagger2locustio/parsers/json_parsers/__pycache__/swagger_v2.cpython-38.pyc
swagger2locustio/strategy/__init__.py
swagger2locustio/strategy/base_strategy.py
swagger2locustio/strategy/__pycache__/__init__.cpython-38.pyc
swagger2locustio/strategy/__pycache__/base_strategy.cpython-38-pytest-5.4.1.pyc
swagger2locustio/strategy/__pycache__/base_strategy.cpython-38.pyc
swagger2locustio/strategy/__pycache__/json_strategy.cpython-38-pytest-5.4.1.pyc
swagger2locustio/strategy/__pycache__/json_strategy.cpython-38.pyc
swagger2locustio/templates/__init__.py
swagger2locustio/templates/auth_templates.py
swagger2locustio/templates/constants_templates.py
swagger2locustio/templates/helpers_templates.py
swagger2locustio/templates/locustfile_templates.py
swagger2locustio-0.0.4.dist-info/LICENSE.md
swagger2locustio-0.0.4.dist-info/METADATA
swagger2locustio-0.0.4.dist-info/WHEEL
swagger2locustio-0.0.4.dist-info/entry_points.txt
swagger2locustio-0.0.4.dist-info/top_level.txt
swagger2locustio-0.0.4.dist-info/RECORD
