Metadata-Version: 2.1
Name: swagger2locustio
Version: 0.0.4
Summary: Tool for testing API endpoints that have Open API / Swagger specifications using locustio
Home-page: https://github.com/vsvirsky/swagger2locustio
Author: 
Author-email: 
License: MIT
Platform: UNKNOWN
Classifier: Development Status :: 3 - Alpha
Classifier: Programming Language :: Python :: 3.7
Classifier: Programming Language :: Python :: 3.8
Classifier: License :: OSI Approved :: MIT License
Classifier: Operating System :: OS Independent
Requires-Python: >=3.7
Requires-Dist: Jinja2 (==2.11.2)
Requires-Dist: PyYAML (==5.3.1)
Requires-Dist: coloredlogs (==14.0)
